stctm/__init__.py
stctm/exotune_utilities.py
stctm/pystellspec.py
stctm/pytransmspec.py
stctm/stellar_retrieval_utilities.py
stctm-2.0.1.dist-info/licenses/LICENSE
stctm-2.0.1.dist-info/METADATA
stctm-2.0.1.dist-info/WHEEL
stctm-2.0.1.dist-info/top_level.txt
stctm-2.0.1.dist-info/zip-safe
stctm-2.0.1.dist-info/RECORD
