Metadata-Version: 2.4
Name: stctm
Version: 2.0.1
Summary: Retrievals on small planet transmission spectra affected by stellar contamination and out-of-transit stellar spectra.
Home-page: http://github.com/cpiaulet/stctm
Author: Caroline Piaulet-Ghorayeb
Author-email: carolinepiaulet@uchicago.edu
License: BSD-3-Clause
Project-URL: Bug Tracker, https://github.com/cpiaulet/stctm/issues
Project-URL: Source Code, https://github.com/cpiaulet/stctm/
Requires-Python: >=3.9.7
License-File: LICENSE
Requires-Dist: astropy
Requires-Dist: corner
Requires-Dist: emcee
Requires-Dist: h5py
Requires-Dist: matplotlib
Requires-Dist: numpy<2.0
Requires-Dist: pandas
Requires-Dist: pysynphot
Requires-Dist: scipy
Requires-Dist: tqdm
Dynamic: license-file
